Workbook
Name Slicer_Branch: #N/A
Name Slicer_Category1: #N/A
Name Slicer_Status: #N/A

Sheet Dashboard Summary
A1: تقرير محفظة التمويل والأداء - شركة إي تمويلكم (نموذج تحليلي للإدارة)
E2: ما هو إجمالي حجم المحفظة التمويلية للشركة، وقديش إجمالي الرصيد المتبقي بذمّة العملاء
A3: ملخص المؤشرات الرئيسية (KPIs)
A4: المؤشر | B4: القيمة
A5: إجمالي محفظة التمويل | B5: =SUM('Raw Data'!F2:F11) -> 54000
A6: إجمالي القروض النشطة | B6: =COUNTIF('Raw Data'!I2:I11, "Active") -> 7
A7: متوسط مبلغ القرض | B7: =AVERAGE('Raw Data'!F2:F11) -> 5400
A8: إجمالي الرصيد المتبقي | B8: =SUM('Raw Data'!K2:K11) -> 36500
A11: توزيع المحفظة حسب الفروع
A12: الفرع | B12: إجمالي التمويل
A13: عمان | B13: =SUMIF('Raw Data'!C$2:C$11, A13, 'Raw Data'!F$2:F$11) -> 15000
A14: الزرقاء | B14: =SUMIF('Raw Data'!C$2:C$11, A14, 'Raw Data'!F$2:F$11) -> 12500
A15: العقبة | B15: =SUMIF('Raw Data'!C$2:C$11, A15, 'Raw Data'!F$2:F$11) -> 10000
A16: إربد | B16: =SUMIF('Raw Data'!C$2:C$11, A16, 'Raw Data'!F$2:F$11) -> 9000
A17: الكرك | B17: =SUMIF('Raw Data'!C$2:C$11, A17, 'Raw Data'!F$2:F$11) -> 7500

Sheet Category&Loan Amount
A3: Row Labels | B3: Sum of Loan Amount (JOD)
A4: قرض تجاري صغير | B4: 19500
A5: تمويل زراعي | B5: 15500
A6: تمويل مهني | B6: 10000
A7: تمويل نسائي | B7: 9000
A8: Grand Total | B8: 54000

Sheet repayment ratios of Categorys
A3: Row Labels | B3: Sum of Repayment ratio
A4: Active | B4: 1.6385917
A5: Completed | B5: 1
A6: Delayed | B6: 0.26136364
A7: Defaulted | B7: 0.11314985
A8: Grand Total | B8: 3.0131052

Sheet Total AVERAGE OF LOAN 
A3: Row Labels | B3: Average of Loan Amount (JOD) | C3: Average of Company Average
A4: تمويل زراعي | B4: 7750 | C4: 5400
A5: قرض تجاري صغير | B5: 6500 | C5: 5400
A6: تمويل مهني | B6: 5000 | C6: 5400
A7: تمويل نسائي | B7: 3000 | C7: 5400
A8: Grand Total | B8: 5400 | C8: 5400

Sheet Sheet3
A3: Row Labels | B3: Sum of Loan approval rate | C3: Sum of Remaining Balance
A4: تمويل زراعي | B4: 17050 | C4: 11700
A5: تمويل مهني | B5: 10900 | C5: 9600
A6: تمويل نسائي | B6: 9720 | C6: 7900
A7: قرض تجاري صغير | B7: 21305 | C7: 7300
A8: Grand Total | B8: 58975 | C8: 36500

Sheet Total funding for branch
A3: Row Labels | B3: Sum of Loan Amount (JOD)
A4: عمان | B4: 15000
A5: الزرقاء | B5: 12500
A6: العقبة | B6: 10000
A7: إربد | B7: 9000
A8: الكرك | B8: 7500
A9: Grand Total | B9: 54000

Sheet Raw Data
A1: Loan ID | B1: Client Name | C1: Branch | D1: Category | E1: Disbursed Date | F1: Loan Amount (JOD) | G1: Interest Rate | H1: Interest rate (JOD) | I1: Status | J1: Monthly Installment | K1: Remaining Balance | L1: Loan approval rate | M1: Repayment ratio | N1: Company Average
A2: 1001 | B2: أحمد محمود | C2: عمان | D2: قرض تجاري صغير | E2: 45672 | F2: 5000 | G2: 0.09 | H2: =F2*G2 -> 450 | I2: Active | J2: 450 | K2: 3200 | L2: =F2+H2 -> 5450 | M2: =(L2 - K2) / L2 -> 0.41284404 | N2: =AVERAGE($F$2:$F$11) -> 5400
A3: 1002 | B3: فاطمة علي | C3: إربد | D3: تمويل نسائي | E3: 45698 | F3: 3000 | G3: 0.08 | H3: =F3*G3 -> 240 | I3: Active | J3: 270 | K3: 2100 | L3: =F3+H3 -> 3240 | M3: =(L3 - K3) / L3 -> 0.35185185 | N3: =AVERAGE($F$2:$F$11) -> 5400
A4: 1003 | B4: خالد حسن | C4: الزرقاء | D4: تمويل زراعي | E4: 45601 | F4: 8000 | G4: 0.1 | H4: =F4*G4 -> 800 | I4: Delayed | J4: 700 | K4: 6500 | L4: =F4+H4 -> 8800 | M4: =(L4 - K4) / L4 -> 0.26136364 | N4: =AVERAGE($F$2:$F$11) -> 5400
A5: 1004 | B5: سارة محمد | C5: عمان | D5: تمويل مهني | E5: 45717 | F5: 4000 | G5: 0.09 | H5: =F5*G5 -> 360 | I5: Active | J5: 360 | K5: 3800 | L5: =F5+H5 -> 4360 | M5: =(L5 - K5) / L5 -> 0.12844037 | N5: =AVERAGE($F$2:$F$11) -> 5400
A6: 1005 | B6: عمر ابراهيم | C6: العقبة | D6: قرض تجاري صغير | E6: 45524 | F6: 10000 | G6: 0.095 | H6: =F6*G6 -> 950 | I6: Completed | J6: 900 | K6: 0 | L6: =F6+H6 -> 10950 | M6: =(L6 - K6) / L6 -> 1 | N6: =AVERAGE($F$2:$F$11) -> 5400
A7: 1006 | B7: نور الدين | C7: إربد | D7: تمويل نسائي | E7: 45728 | F7: 2500 | G7: 0.08 | H7: =F7*G7 -> 200 | I7: Active | J7: 225 | K7: 2400 | L7: =F7+H7 -> 2700 | M7: =(L7 - K7) / L7 -> 0.11111111 | N7: =AVERAGE($F$2:$F$11) -> 5400
A8: 1007 | B8: يوسف أحمد | C8: الكرك | D8: تمويل زراعي | E8: 45575 | F8: 7500 | G8: 0.1 | H8: =F8*G8 -> 750 | I8: Active | J8: 650 | K8: 5200 | L8: =F8+H8 -> 8250 | M8: =(L8 - K8) / L8 -> 0.36969697 | N8: =AVERAGE($F$2:$F$11) -> 5400
A9: 1008 | B9: ريم خالد | C9: عمان | D9: تمويل مهني | E9: 45662 | F9: 6000 | G9: 0.09 | H9: =F9*G9 -> 540 | I9: Defaulted | J9: 540 | K9: 5800 | L9: =F9+H9 -> 6540 | M9: =(L9 - K9) / L9 -> 0.11314985 | N9: =AVERAGE($F$2:$F$11) -> 5400
A10: 1009 | B10: طارق زيد | C10: الزرقاء | D10: قرض تجاري صغير | E10: 45706 | F10: 4500 | G10: 0.09 | H10: =F10*G10 -> 405 | I10: Active | J10: 405 | K10: 4100 | L10: =F10+H10 -> 4905 | M10: =(L10 - K10) / L10 -> 0.16411825 | N10: =AVERAGE($F$2:$F$11) -> 5400
A11: 1010 | B11: بيان عبد الله | C11: إربد | D11: تمويل نسائي | E11: 45736 | F11: 3500 | G11: 0.08 | H11: =F11*G11 -> 280 | I11: Active | J11: 315 | K11: 3400 | L11: =F11+H11 -> 3780 | M11: =(L11 - K11) / L11 -> 0.1005291 | N11: =AVERAGE($F$2:$F$11) -> 5400
A12: Total | F12: =SUBTOTAL(109,Table1[Loan Amount (JOD)]) -> 54000 | I12: =SUBTOTAL(103,Table1[Status]) -> 10 | J12: =SUBTOTAL(109,Table1[Monthly Installment]) -> 4815 | K12: =SUBTOTAL(109,Table1[Remaining Balance]) -> 36500 | L12: =SUBTOTAL(109,Table1[Loan approval rate]) -> 58975
I13: =COUNTIF(I2:I11,"Active") -> 7

Sheet QQ

Sheet Dashboard
A1: Client Financing & Financial Commitment Dashboard)
